rtl/spi_slave.v
`timescale 1ns / 1ps

module spi_slave #(
    parameter DATA_WIDTH = 8,
    parameter MSB_FIRST  = 1
)(
    input  wire                  sclk,
    input  wire                  cs_n,
    input  wire                  mosi,
    input  wire                  rst,
    input  wire [DATA_WIDTH-1:0] tx_data,
    input  wire                  cpol,
    input  wire                  cpha,

    output reg                   miso,
    output reg  [DATA_WIDTH-1:0] rx_data,
    output reg                   rx_valid
);

    reg [DATA_WIDTH-1:0] tx_reg;
    reg [DATA_WIDTH-1:0] rx_reg;
    reg [$clog2(DATA_WIDTH):0] bit_cnt; // bit_cnt is number of bit already sampled

    wire sample_clk_internal;
    wire shift_clk_internal;

    // Mode 0 (0,0): Sample Rising,  Shift Falling
    // Mode 1 (0,1): Shift Rising,   Sample Falling
    // Mode 2 (1,0): Sample Falling, Shift Rising
    // Mode 3 (1,1): Shift Falling,  Sample Rising

    assign sample_clk_internal = (cpol == cpha) ? sclk : ~sclk;
    assign shift_clk_internal  = (cpol == cpha) ? ~sclk : sclk;

    always @(negedge cs_n or posedge rst) begin
        if (rst) begin
            bit_cnt <= 0;
            miso    <= 1'bz;
            rx_valid <= 0;
            rx_reg  <= 0;
        end else begin
            bit_cnt <= 0;
            tx_reg  <= tx_data; // Load data to send
            rx_valid <= 0;

            if (cpha == 0) begin
                if (MSB_FIRST)
                    miso <= tx_data[DATA_WIDTH-1];
                else
                    miso <= tx_data[0];
            end
        end
    end

    always @(posedge sample_clk_internal or posedge cs_n or posedge rst) begin
        if (rst) begin
            rx_reg <= 0;
        end else if (cs_n) begin
            // Reset logic handled in negedge cs_n block
        end else begin
            if (bit_cnt < DATA_WIDTH) begin
                if (MSB_FIRST)
                    rx_reg <= {rx_reg[DATA_WIDTH-2:0], mosi};
                else
                    rx_reg <= {mosi, rx_reg[DATA_WIDTH-1:1]};

                bit_cnt <= bit_cnt + 1;
            end
        end
    end

    always @(posedge shift_clk_internal or posedge cs_n or posedge rst) begin
        if (rst) begin
            miso <= 1'bz;
        end else if (cs_n) begin
            miso <= 1'bz;
        end else begin
            // In CPHA=0: This edge happens AFTER sample. bit_cnt is 1. We want Bit 6. (7-1=6)
            // In CPHA=1: This edge happens BEFORE sample. bit_cnt is 0. We want Bit 7. (7-0=7)
            if (bit_cnt < DATA_WIDTH) begin
                if (MSB_FIRST)
                    miso <= tx_reg[DATA_WIDTH - 1 - bit_cnt];
                else
                    miso <= tx_reg[bit_cnt];
            end
        end
    end

    always @(posedge cs_n) begin
        if (!rst && bit_cnt == DATA_WIDTH) begin
            rx_data <= rx_reg;
            rx_valid <= 1;
        end else begin
            rx_valid <= 0;
        end
    end

endmodule

testbench/spi_slave_tb.v
`timescale 1ns / 1ps

module spi_slave_tb;

    parameter DATA_WIDTH = 8;

    reg                   sclk;
    reg                   cs_n;
    reg                   mosi;
    reg                   rst;
    reg                   cpol;
    reg                   cpha;
    reg [DATA_WIDTH-1:0]  tx_data;

    wire                  miso;
    wire [DATA_WIDTH-1:0] rx_data;
    wire                  rx_valid;

    // Testbench tracking variables
    reg [DATA_WIDTH-1:0] master_rx_reg;
    integer i;

    spi_slave #(
        .DATA_WIDTH(DATA_WIDTH),
        .MSB_FIRST(1)
    ) dut (
        .sclk(sclk),
        .cs_n(cs_n),
        .mosi(mosi),
        .rst(rst),
        .cpol(cpol),
        .cpha(cpha),
        .tx_data(tx_data),
        .miso(miso),
        .rx_data(rx_data),
        .rx_valid(rx_valid)
    );

    task run_spi_transaction;
        input [DATA_WIDTH-1:0] master_out_data;
        input [DATA_WIDTH-1:0] expected_slave_out;// expected MISO
        input mode_cpol;
        input mode_cpha;
        begin
            cpol = mode_cpol;
            cpha = mode_cpha;
            sclk = cpol;
            master_rx_reg = 0;
            #20;
            $display("[Time %0t] Starting Mode (CPOL=%b, CPHA=%b) | MOSI: 0x%h | Exp MISO: 0x%h",
                     $time, cpol, cpha, master_out_data, expected_slave_out);

            cs_n = 0;

            if (cpha == 0) begin
                mosi = master_out_data[DATA_WIDTH-1];
                #10;
            end else begin
                #10;
            end

            for (i = 0; i < DATA_WIDTH; i = i + 1) begin
                if (cpha == 0) begin
                    sclk = ~sclk;
                    master_rx_reg = {master_rx_reg[DATA_WIDTH-2:0], miso};
                    #10;

                    sclk = ~sclk;
                    if (i < DATA_WIDTH-1)
                        mosi = master_out_data[DATA_WIDTH - 2 - i];
                    #10;

                end else begin
                    sclk = ~sclk;
                    mosi = master_out_data[DATA_WIDTH - 1 - i];
                    #10;

                    sclk = ~sclk;
                    master_rx_reg = {master_rx_reg[DATA_WIDTH-2:0], miso};
                    #10;
                end
            end

            #10;
            cs_n = 1;
            mosi = 0;
            sclk = cpol;
            #20;

            if (rx_valid && rx_data == master_out_data)
                $display("    [PASS] Slave RX: 0x%h", rx_data);
            else
                $display("    [FAIL] Slave RX: 0x%h (Expected: 0x%h)", rx_data, master_out_data);

            if (master_rx_reg == expected_slave_out)
                $display("    [PASS] Master RX: 0x%h", master_rx_reg);
            else
                $display("    [FAIL] Master RX: 0x%h (Expected: 0x%h)",
                    master_rx_reg, expected_slave_out);
        end
    endtask

    initial begin
        $dumpfile("spi_slave_test.vcd");
        $dumpvars(0, spi_slave_tb);

        // Initialize
        rst = 1;
        sclk = 0;
        cs_n = 1;
        mosi = 0;
        cpol = 0;
        cpha = 0;
        tx_data = 0;

        #20;
        rst = 0;
        #20;

        $display("");
        $display("TEST CASE 1: Standard Modes (8-bit)");
        $display("");
        // Mode 0: Master sends 0xA1, Slave sends 0x55
        tx_data = 8'h55;
        run_spi_transaction(8'hA1, 8'h55, 0, 0);

        // Mode 1: Master sends 0xB2, Slave sends 0xAA
        tx_data = 8'hAA;
        run_spi_transaction(8'hB2, 8'hAA, 0, 1);

        // Mode 2: Master sends 0xC3, Slave sends 0x33
        tx_data = 8'h33;
        run_spi_transaction(8'hC3, 8'h33, 1, 0);

        // Mode 3: Master sends 0xD4, Slave sends 0xCC
        tx_data = 8'hCC;
        run_spi_transaction(8'hD4, 8'hCC, 1, 1);


        $display("");
        $display("");
        $display("TEST CASE 2: Back-to-Back Transfers (Stress Test)");
        $display("");
        // Transfer 1
        tx_data = 8'h11;
        cpol=0; cpha=0; sclk=0;
        cs_n = 0;
        mosi = 1;
        #10;
        repeat(8) begin sclk=1; #10; sclk=0; #10; end
        // End Transaction 1
        cs_n = 1;
        #10;
        // Transfer 2
        tx_data = 8'hFF;
        cs_n = 0;
        #10;
        repeat(8) begin sclk=1; #10; sclk=0; #10; end
        cs_n = 1;
        #10;
        if (rx_valid) $display("    [PASS] Back-to-Back Valid Pulse Detected");
        else          $display("    [FAIL] Back-to-Back Valid Pulse Missed");


        $display("");
        $display("");
        $display("TEST CASE 3: Reset in Middle of Transaction");
        $display("");
        cpol=0; cpha=0; sclk=0;
        cs_n = 0;
        #10;
        // Clock 4 times (Halfway)
        repeat(4) begin sclk=1; #10; sclk=0; #10; end
        $display("    [INFO] Asserting Reset mid-transfer...");
        rst = 1;
        #10;
        rst = 0;
        cs_n = 1;// End transaction
        #10;
        if (rx_valid == 0) $display("    [PASS] No Valid Pulse (Correctly Aborted)");
        else               $display("    [FAIL] Valid Pulse generated despite Reset");

        $display("");
        $display("ALL TESTS COMPLETE");
        $finish;
    end

endmodule

waveform/slave_tb.vcd
$date
	Thu Nov 27 22:02:23 2025
$end
$version
	Icarus Verilog
$end
$timescale
	1ps
$end
$scope module spi_slave_tb $end
$var wire 1 ! rx_valid $end
$var wire 8 " rx_data [7:0] $end
$var wire 1 # miso $end
$var parameter 32 $ DATA_WIDTH $end
$var reg 1 % cpha $end
$var reg 1 & cpol $end
$var reg 1 ' cs_n $end
$var reg 8 ( master_rx_reg [7:0] $end
$var reg 1 ) mosi $end
$var reg 1 * rst $end
$var reg 1 + sclk $end
$var reg 8 , tx_data [7:0] $end
$var integer 32 - i [31:0] $end
$scope module dut $end
$var wire 1 % cpha $end
$var wire 1 & cpol $end
$var wire 1 ' cs_n $end
$var wire 1 ) mosi $end
$var wire 1 * rst $end
$var wire 1 + sclk $end
$var wire 8 . tx_data [7:0] $end
$var wire 1 / shift_clk_internal $end
$var wire 1 0 sample_clk_internal $end
$var parameter 32 1 DATA_WIDTH $end
$var parameter 32 2 MSB_FIRST $end
$var reg 4 3 bit_cnt [3:0] $end
$var reg 1 # miso $end
$var reg 8 4 rx_data [7:0] $end
$var reg 8 5 rx_reg [7:0] $end
$var reg 1 ! rx_valid $end
$var reg 8 6 tx_reg [7:0] $end
$upscope $end
$scope task run_spi_transaction $end
$var reg 8 7 expected_slave_out [7:0] $end
$var reg 8 8 master_out_data [7:0] $end
$var reg 1 9 mode_cpha $end
$var reg 1 : mode_cpol $end
$upscope $end
$upscope $end
$enddefinitions $end
$comment Show the parameter values. $end
$dumpall
b1 2
b1000 1
b1000 $
$end
#0
$dumpvars
x:
x9
bx 8
bx 7
bx 6
b0 5
bx 4
b0 3
00
1/
b0 .
bx -
b0 ,
0+
1*
0)
bx (
1'
0&
0%
z#
bx "
0!
$end
#20000
0*
#40000
b0 (
09
0:
b1010101 7
b10100001 8
b1010101 ,
b1010101 .
#60000
0#
b1010101 6
1)
0'
#70000
b1 3
b1 5
0/
10
1+
b0 -
#80000
1#
1/
00
0)
0+
#90000
b10 3
b10 5
0/
10
b1 (
1+
b1 -
#100000
0#
1/
00
1)
0+
#110000
b11 3
b101 5
0/
10
b10 (
1+
b10 -
#120000
1#
1/
00
0)
0+
#130000
b100 3
b1010 5
0/
10
b101 (
1+
b11 -
#140000
0#
1/
00
0+
#150000
b101 3
b10100 5
0/
10
b1010 (
1+
b100 -
#160000
1#
1/
00
0+
#170000
b110 3
b101000 5
0/
10
b10101 (
1+
b101 -
#180000
0#
1/
00
0+
#190000
b111 3
b1010000 5
0/
10
b101010 (
1+
b110 -
#200000
1#
1/
00
1)
0+
#210000
b1000 3
b10100001 5
0/
10
b1010101 (
1+
b111 -
#220000
1/
00
0+
#230000
b1000 -
#240000
1!
b10100001 "
b10100001 4
z#
0)
1'
#260000
10
0/
b0 (
1%
19
b10101010 7
b10110010 8
b10101010 ,
b10101010 .
#280000
0!
b10101010 6
b0 3
0'
#290000
1#
00
1/
1)
1+
b0 -
#300000
b1 3
b1000011 5
10
0/
b1 (
0+
#310000
0#
00
1/
0)
1+
b1 -
#320000
b10 3
b10000110 5
10
0/
b10 (
0+
#330000
1#
00
1/
1)
1+
b10 -
#340000
b11 3
b1101 5
10
0/
b101 (
0+
#350000
0#
00
1/
1+
b11 -
#360000
b100 3
b11011 5
10
0/
b1010 (
0+
#370000
1#
00
1/
0)
1+
b100 -
#380000
b101 3
b110110 5
10
0/
b10101 (
0+
#390000
0#
00
1/
1+
b101 -
#400000
b110 3
b1101100 5
10
0/
b101010 (
0+
#410000
1#
00
1/
1)
1+
b110 -
#420000
b111 3
b11011001 5
10
0/
b1010101 (
0+
#430000
0#
00
1/
0)
1+
b111 -
#440000
b1000 3
b10110010 5
10
0/
b10101010 (
0+
#450000
b1000 -
#460000
1!
b10110010 "
b10110010 4
z#
1'
#480000
00
1/
b0 (
1+
0%
1&
09
1:
b110011 7
b11000011 8
b110011 ,
b110011 .
#500000
0#
0!
b110011 6
b0 3
1)
0'
#510000
b1 3
b1100101 5
10
0/
0+
b0 -
#520000
00
1/
1+
#530000
b10 3
b11001011 5
10
0/
0+
b1 -
#540000
1#
00
1/
0)
1+
#550000
b11 3
b10010110 5
10
0/
b1 (
0+
b10 -
#560000
00
1/
1+
#570000
b100 3
b101100 5
10
0/
b11 (
0+
b11 -
#580000
0#
00
1/
1+
#590000
b101 3
b1011000 5
10
0/
b110 (
0+
b100 -
#600000
00
1/
1+
#610000
b110 3
b10110000 5
10
0/
b1100 (
0+
b101 -
#620000
1#
00
1/
1)
1+
#630000
b111 3
b1100001 5
10
0/
b11001 (
0+
b110 -
#640000
00
1/
1+
#650000
b1000 3
b11000011 5
10
0/
b110011 (
0+
b111 -
#660000
00
1/
1+
#670000
b1000 -
#680000
1!
b11000011 "
b11000011 4
z#
0)
1'
#700000
10
0/
b0 (
1%
19
b11001100 7
b11010100 8
b11001100 ,
b11001100 .
#720000
0!
b11001100 6
b0 3
0'
#730000
1#
1/
00
1)
0+
b0 -
#740000
b1 3
b10000111 5
0/
10
b1 (
1+
#750000
1/
00
0+
b1 -
#760000
b10 3
b1111 5
0/
10
b11 (
1+
#770000
0#
1/
00
0)
0+
b10 -
#780000
b11 3
b11110 5
0/
10
b110 (
1+
#790000
1/
00
1)
0+
b11 -
#800000
b100 3
b111101 5
0/
10
b1100 (
1+
#810000
1#
1/
00
0)
0+
b100 -
#820000
b101 3
b1111010 5
0/
10
b11001 (
1+
#830000
1/
00
1)
0+
b101 -
#840000
b110 3
b11110101 5
0/
10
b110011 (
1+
#850000
0#
1/
00
0)
0+
b110 -
#860000
b111 3
b11101010 5
0/
10
b1100110 (
1+
#870000
1/
00
0+
b111 -
#880000
b1000 3
b11010100 5
0/
10
b11001100 (
1+
#890000
b1000 -
#900000
1!
b11010100 "
b11010100 4
z#
1'
#920000
0#
0!
b10001 6
b0 3
1/
00
1)
0'
0+
0%
0&
b10001 ,
b10001 .
#930000
b1 3
b10101001 5
0/
10
1+
#940000
1/
00
0+
#950000
b10 3
b1010011 5
0/
10
1+
#960000
1/
00
0+
#970000
b11 3
b10100111 5
0/
10
1+
#980000
1#
1/
00
0+
#990000
b100 3
b1001111 5
0/
10
1+
#1000000
0#
1/
00
0+
#1010000
b101 3
b10011111 5
0/
10
1+
#1020000
1/
00
0+
#1030000
b110 3
b111111 5
0/
10
1+
#1040000
1/
00
0+
#1050000
b111 3
b1111111 5
0/
10
1+
#1060000
1#
1/
00
0+
#1070000
b1000 3
b11111111 5
0/
10
1+
#1080000
1/
00
0+
#1090000
1!
b11111111 "
b11111111 4
z#
1'
#1100000
1#
0!
b11111111 6
b0 3
0'
b11111111 ,
b11111111 .
#1110000
b1 3
0/
10
1+
#1120000
1/
00
0+
#1130000
b10 3
0/
10
1+
#1140000
1/
00
0+
#1150000
b11 3
0/
10
1+
#1160000
1/
00
0+
#1170000
b100 3
0/
10
1+
#1180000
1/
00
0+
#1190000
b101 3
0/
10
1+
#1200000
1/
00
0+
#1210000
b110 3
0/
10
1+
#1220000
1/
00
0+
#1230000
b111 3
0/
10
1+
#1240000
1/
00
0+
#1250000
b1000 3
0/
10
1+
#1260000
1/
00
0+
#1270000
1!
z#
1'
#1280000
1#
0!
b0 3
0'
#1290000
b1 3
0/
10
1+
#1300000
1/
00
0+
#1310000
b10 3
0/
10
1+
#1320000
1/
00
0+
#1330000
b11 3
0/
10
1+
#1340000
1/
00
0+
#1350000
b100 3
0/
10
1+
#1360000
1/
00
0+
#1370000
b0 5
z#
b0 3
1*
#1380000
1'
0*
